odoo/addons/test_shopinvader_payment/README.rst
odoo/addons/test_shopinvader_payment/__init__.py
odoo/addons/test_shopinvader_payment/__manifest__.py
odoo/addons/test_shopinvader_payment/i18n/test_shopinvader_payment.pot
odoo/addons/test_shopinvader_payment/readme/CONTRIBUTORS.rst
odoo/addons/test_shopinvader_payment/readme/DESCRIPTION.rst
odoo/addons/test_shopinvader_payment/static/description/index.html
odoo/addons/test_shopinvader_payment/tests/__init__.py
odoo/addons/test_shopinvader_payment/tests/test_shopinvader_payment_manual.py
odoo/addons/test_shopinvader_payment/tests/test_shopinvader_payment_stripe.py
odoo/addons/test_shopinvader_payment/tests/test_shopinvader_quotation_payment.py
odoo12_addon_test_shopinvader_payment-12.0.3.0.0.dist-info/METADATA
odoo12_addon_test_shopinvader_payment-12.0.3.0.0.dist-info/WHEEL
odoo12_addon_test_shopinvader_payment-12.0.3.0.0.dist-info/top_level.txt
odoo12_addon_test_shopinvader_payment-12.0.3.0.0.dist-info/RECORD
